mtrf/__init__.py
mtrf/matrices.py
mtrf/model.py
mtrf/stats.py
mtrf-2.1.2.dist-info/licenses/LICENSE
mtrf-2.1.2.dist-info/METADATA
mtrf-2.1.2.dist-info/WHEEL
mtrf-2.1.2.dist-info/top_level.txt
mtrf-2.1.2.dist-info/RECORD
