Metadata-Version: 2.4
Name: mtrf
Version: 2.1.2
Summary: Tools for modeling brain responses using (multivariate)temporal response functions.
Home-page: http://github.com/powerfulbean/mTRFpy
Author: powerfulbean
License: MIT
Classifier: Programming Language :: Python :: 3
Classifier: License :: OSI Approved :: MIT License
Classifier: Operating System :: OS Independent
Requires-Python: >=3.9
License-File: LICENSE
Requires-Dist: numpy
Requires-Dist: array-api-compat
Provides-Extra: testing
Requires-Dist: requests; extra == "testing"
Requires-Dist: flake8; extra == "testing"
Requires-Dist: black; extra == "testing"
Requires-Dist: dask; extra == "testing"
Requires-Dist: array-api-strict; extra == "testing"
Requires-Dist: pytest; extra == "testing"
Requires-Dist: tqdm; extra == "testing"
Requires-Dist: matplotlib; extra == "testing"
Requires-Dist: scipy; extra == "testing"
Requires-Dist: black; extra == "testing"
Provides-Extra: docs
Requires-Dist: sphinx; extra == "docs"
Requires-Dist: sphinx_rtd_theme; extra == "docs"
Requires-Dist: mne; extra == "docs"
Requires-Dist: matplotlib; extra == "docs"
Provides-Extra: full
Requires-Dist: mtrf[testing]; extra == "full"
Requires-Dist: mtrf[docs]; extra == "full"
Dynamic: author
Dynamic: classifier
Dynamic: description
Dynamic: description-content-type
Dynamic: home-page
Dynamic: license
Dynamic: license-file
Dynamic: provides-extra
Dynamic: requires-dist
Dynamic: requires-python
Dynamic: summary
